autr/__init__.py
autr/base.py
autr/csv.py
autr/json.py
autr/text.py
autr/yaml.py
autr-0.1.0.dist-info/WHEEL
autr-0.1.0.dist-info/METADATA
autr-0.1.0.dist-info/RECORD
