Metadata-Version: 2.1
Name: autr
Version: 0.1.0
Summary: Automatic file reader
Author: Gabriel Guarisa
Author-email: gabrielguarisa@gmail.com
Requires-Python: >=3.8,<3.11
Classifier: Programming Language :: Python :: 3
Classifier: Programming Language :: Python :: 3.8
Classifier: Programming Language :: Python :: 3.9
Classifier: Programming Language :: Python :: 3.10
Requires-Dist: PyYAML (>=6.0,<7.0)
Requires-Dist: pandas (>=1.3.5,<2.0.0)
